LICENSE.BAYKIT
README.md
setup.py
bayserver_docker_http/__init__.py
bayserver_docker_http/htp_docker.py
bayserver_docker_http/htp_port_docker.py
bayserver_docker_http/htp_warp_docker.py
bayserver_docker_http.egg-info/PKG-INFO
bayserver_docker_http.egg-info/SOURCES.txt
bayserver_docker_http.egg-info/dependency_links.txt
bayserver_docker_http.egg-info/requires.txt
bayserver_docker_http.egg-info/top_level.txt
bayserver_docker_http/h1/__init__.py
bayserver_docker_http/h1/h1_command.py
bayserver_docker_http/h1/h1_command_handler.py
bayserver_docker_http/h1/h1_command_unpacker.py
bayserver_docker_http/h1/h1_handler.py
bayserver_docker_http/h1/h1_inbound_handler.py
bayserver_docker_http/h1/h1_packet.py
bayserver_docker_http/h1/h1_packet_factory.py
bayserver_docker_http/h1/h1_packet_unpacker.py
bayserver_docker_http/h1/h1_protocol_handler.py
bayserver_docker_http/h1/h1_type.py
bayserver_docker_http/h1/h1_warp_handler.py
bayserver_docker_http/h1/command/__init__.py
bayserver_docker_http/h1/command/cmd_content.py
bayserver_docker_http/h1/command/cmd_end_content.py
bayserver_docker_http/h1/command/cmd_header.py
bayserver_docker_http/h2/__init__.py
bayserver_docker_http/h2/h2_command.py
bayserver_docker_http/h2/h2_command_handler.py
bayserver_docker_http/h2/h2_command_unpacker.py
bayserver_docker_http/h2/h2_error_code.py
bayserver_docker_http/h2/h2_flags.py
bayserver_docker_http/h2/h2_handler.py
bayserver_docker_http/h2/h2_inbound_handler.py
bayserver_docker_http/h2/h2_packet.py
bayserver_docker_http/h2/h2_packet_factory.py
bayserver_docker_http/h2/h2_packet_unpacker.py
bayserver_docker_http/h2/h2_protocol_handler.py
bayserver_docker_http/h2/h2_settings.py
bayserver_docker_http/h2/h2_type.py
bayserver_docker_http/h2/h2_warp_handler.py
bayserver_docker_http/h2/header_block.py
bayserver_docker_http/h2/header_block_analyzer.py
bayserver_docker_http/h2/header_block_builder.py
bayserver_docker_http/h2/header_table.py
bayserver_docker_http/h2/command/__init__.py
bayserver_docker_http/h2/command/cmd_data.py
bayserver_docker_http/h2/command/cmd_go_away.py
bayserver_docker_http/h2/command/cmd_headers.py
bayserver_docker_http/h2/command/cmd_ping.py
bayserver_docker_http/h2/command/cmd_preface.py
